<?xml version="1.0" encoding="utf-8" ?>
<dwsync>
<file name="editor_plugin.js" server="ftp.domeneshop.no//www/wp-content/" local="129400771482896980" remote="129400736400000000" />
<file name="icon.png" server="ftp.domeneshop.no//www/wp-content/" local="129400771483066990" remote="129400736400000000" />
<file name="langs.php" server="ftp.domeneshop.no//www/wp-content/" local="129400771483196997" remote="129400736400000000" />
<file name="popup.php" server="ftp.domeneshop.no//www/wp-content/" local="129400771483567019" remote="129400736400000000" />
<file name="tinymce.js" server="ftp.domeneshop.no//www/wp-content/" local="129400771483737028" remote="129400736400000000" />
<file name="tinymce.php" server="ftp.domeneshop.no//www/wp-content/" local="129400771484187054" remote="129400736400000000" />
<file name="editor_plugin.js" server="webcluster02.webhuset.no/www/" local="129400771482896980" remote="129459395400000000" />
<file name="icon.png" server="webcluster02.webhuset.no/www/" local="129400771483066990" remote="129459395400000000" />
<file name="langs.php" server="webcluster02.webhuset.no/www/" local="129400771483196997" remote="129459395400000000" />
<file name="popup.php" server="webcluster02.webhuset.no/www/" local="129400771483567019" remote="129459395400000000" />
<file name="tinymce.js" server="webcluster02.webhuset.no/www/" local="129400771483737028" remote="129459395400000000" />
<file name="tinymce.php" server="webcluster02.webhuset.no/www/" local="129400771484187054" remote="129459395400000000" />
<file name="editor_plugin.js" server="ftp.domeneshop.no//www/wordpress/" local="129400771482896980" remote="129416573400000000" />
<file name="icon.png" server="ftp.domeneshop.no//www/wordpress/" local="129400771483066990" remote="129416573400000000" />
<file name="langs.php" server="ftp.domeneshop.no//www/wordpress/" local="129400771483196997" remote="129416573400000000" />
<file name="popup.php" server="ftp.domeneshop.no//www/wordpress/" local="129400771483567019" remote="129416573400000000" />
<file name="tinymce.js" server="ftp.domeneshop.no//www/wordpress/" local="129400771483737028" remote="129416573400000000" />
<file name="tinymce.php" server="ftp.domeneshop.no//www/wordpress/" local="129400771484187054" remote="129416573400000000" />
</dwsync>